satorix_django/__init__.py
satorix_django/__main__.py
satorix_django/__version__.py
satorix_django/config.py
satorix_django/settings.py
satorix_django/install/.buildpacks
satorix_django/install/.gitlab-ci.yml
satorix_django/install/.ruby-version
satorix_django/install/Gemfile
satorix_django/install/Gemfile.lock
satorix_django/install/Procfile
satorix_django/install/requirements.txt
satorix_django/install/config/passenger_standalone/nginx.conf.erb
satorix_django/install/config/passenger_standalone/includes/authentication.erb
satorix_django/install/config/passenger_standalone/includes/django_asset_pipeline.erb
satorix_django/install/config/passenger_standalone/includes/page_level_redirects.erb
satorix_django/install/config/passenger_standalone/includes/proxy_configuration.erb
satorix_django/install/public/Passengerfile.json
satorix_django-0.1.10.dist-info/METADATA
satorix_django-0.1.10.dist-info/WHEEL
satorix_django-0.1.10.dist-info/entry_points.txt
satorix_django-0.1.10.dist-info/top_level.txt
satorix_django-0.1.10.dist-info/RECORD
