Metadata-Version: 2.1
Name: satorix-django
Version: 0.1.10
Summary: Configure Django application for Satorix environment
Home-page: https://github.com/satorix/satorix-django
Author: Satorix
Author-email: tech@satorix.com
License: MIT
Platform: UNKNOWN
Classifier: License :: OSI Approved :: MIT License
Classifier: Programming Language :: Python :: 3
Classifier: Programming Language :: Python :: 3.5
Requires-Dist: django (>=2.2.11)
Requires-Dist: django-heroku
